anitya/__init__.py
anitya/admin.py
anitya/api.py
anitya/api_v2.py
anitya/app.py
anitya/auth.py
anitya/authentication.py
anitya/check_service.py
anitya/compat.py
anitya/config.py
anitya/db/__init__.py
anitya/db/events.py
anitya/db/meta.py
anitya/db/migrations/README.md
anitya/db/migrations/__init__.py
anitya/db/migrations/env.py
anitya/db/migrations/script.py.mako
anitya/db/migrations/versions/136d119ab015_rename_project_latest_known_cursor_to_.py
anitya/db/migrations/versions/16aa7da2764c_add_projectversion_commit_url.py
anitya/db/migrations/versions/1ab95561edae_convert_date_to_rpm.py
anitya/db/migrations/versions/1bf8aead6179_add_check_times.py
anitya/db/migrations/versions/1f839c54e428_add_archive_flag.py
anitya/db/migrations/versions/24b6734e8565_creation_date_on_version.py
anitya/db/migrations/versions/27342bce1d0f_populate_project_version_scheme.py
anitya/db/migrations/versions/2925648d8cc3_add_a_version_prefix_field.py
anitya/db/migrations/versions/2d1aa7ff82a5_remove_code_google_backend.py
anitya/db/migrations/versions/314651690dc7_add_error_counter_to_project.py
anitya/db/migrations/versions/34b9bb5fa388_make_ecosystem_non_nullable.py
anitya/db/migrations/versions/3fae8239eeec_add_an_api_token_table.py
anitya/db/migrations/versions/540bdcf7edbc_convert_github_url_to_owner_project.py
anitya/db/migrations/versions/571bd07533a9_add_insecure_column_to_projects_table.py
anitya/db/migrations/versions/5b8b587d7dbe_add_version_filter_column.py
anitya/db/migrations/versions/5e209766aead_add_release_check_to_project.py
anitya/db/migrations/versions/6ac0e42df937_drop_logs_table.py
anitya/db/migrations/versions/708f6f26b4b6_add_version_pattern.py
anitya/db/migrations/versions/7a8c4aa92678_add_missing_github_owner_project_pairs.py
anitya/db/migrations/versions/8040ef9a9dda_add_a_version_scheme_column_to_projects.py
anitya/db/migrations/versions/8ba7d4c42044_remove_socialauth.py
anitya/db/migrations/versions/8be6e153962c_remove_cursor.py
anitya-2.1.0.dist-info/LICENSE
anitya-2.1.0.dist-info/METADATA
anitya-2.1.0.dist-info/WHEEL
anitya-2.1.0.dist-info/entry_points.txt
anitya-2.1.0.dist-info/RECORD
