Metadata-Version: 2.3
Name: anitya
Version: 2.1.0
Summary: A cross-distribution upstream release monitoring project
License: GPL-2.0-or-later
Author: Pierre-Yves Chibon
Author-email: pingou@pingoured.fr
Maintainer: Michal Konecny
Maintainer-email: mkonecny@redhat.com
Requires-Python: >=3.11.0,<4.0.0
Classifier: License :: OSI Approved :: GNU General Public License v2 or later (GPLv2+)
Classifier: Programming Language :: Python :: 3
Classifier: Programming Language :: Python :: 3.11
Classifier: Programming Language :: Python :: 3.12
Classifier: Programming Language :: Python :: 3.13
Classifier: Programming Language :: Python :: 3.14
Requires-Dist: Flask (>=3.0.0,<4.0.0)
Requires-Dist: Flask-Login (>=0.6.3,<0.7.0)
Requires-Dist: Flask-WTF (>=1.2.1,<2.0.0)
Requires-Dist: Jinja2 (<3.1.7)
Requires-Dist: SQLAlchemy (>=2.0.0,<3.0.0)
Requires-Dist: WTForms (>=3.0.1,<4.0.0)
Requires-Dist: Werkzeug (==3.1.5)
Requires-Dist: alembic (>=1.8.1,<2.0.0)
Requires-Dist: anitya-schema (>=2.0.1,<3.0.0)
Requires-Dist: arrow (>=1.2.3,<2.0.0)
Requires-Dist: authlib (>=1.3.2,<2.0.0)
Requires-Dist: beautifulsoup4 (>=4.11.1,<5.0.0)
Requires-Dist: defusedxml (>=0.7.1,<0.8.0)
Requires-Dist: fedora-messaging (>=3.1.0,<4.0.0)
Requires-Dist: ordered-set (>=4.1.0,<5.0.0)
Requires-Dist: packaging (>=26.0,<27.0)
Requires-Dist: python-dateutil (>=2.8.2,<3.0.0)
Requires-Dist: semver (>=3.0.0,<4.0.0)
Requires-Dist: sseclient (>=0.0.27,<0.0.28)
Requires-Dist: toml (>=0.10.2,<0.11.0)
Requires-Dist: webargs (>=8.7.0,<9.0.0)
Project-URL: Documentation, https://anitya.readthedocs.io
Project-URL: Homepage, https://release-monitoring.org
Project-URL: Repository, https://github.com/fedora-infra/anitya
